CHANGES.rst
MANIFEST.in
README.rst
TODO.rst
setup.py
src/ao/__init__.py
src/ao.social.egg-info/PKG-INFO
src/ao.social.egg-info/SOURCES.txt
src/ao.social.egg-info/dependency_links.txt
src/ao.social.egg-info/namespace_packages.txt
src/ao.social.egg-info/requires.txt
src/ao.social.egg-info/top_level.txt
src/ao.social.egg-info/zip-safe
src/ao/social/__init__.py
src/ao/social/appengine.py
src/ao/social/django.rst
src/ao/social/facebook_.py
src/ao/social/google_.py
src/ao/social/linkedin_.py
src/ao/social/middleware.py
src/ao/social/middleware.rst
src/ao/social/oauth_.py
src/ao/social/tests.py
src/ao/social/twitter_.py
src/ao/social/utils.py
src/ao/social/templatetags/__init__.py
src/ao/social/templatetags/social.py